jupyprint/__init__.py
jupyprint/jupyprint.py
jupyprint-0.1.6.dist-info/LICENSE.txt
jupyprint-0.1.6.dist-info/METADATA
jupyprint-0.1.6.dist-info/WHEEL
jupyprint-0.1.6.dist-info/top_level.txt
jupyprint-0.1.6.dist-info/RECORD
