Metadata-Version: 2.1
Name: jupyprint
Version: 0.1.6
Summary: A simple python package to print markdown and LaTeX equations from code cells in Jupyter notebooks.
Home-page: https://github.com/pxr687/jupyprint
Author: Peter Rush
License: MIT
License-File: LICENSE.txt
Requires-Dist: numpy
Requires-Dist: pandas
Requires-Dist: ipython
